pytcp_message/TcpClient.py
pytcp_message/TcpServer.py
pytcp_message/_RequestHandler.py
pytcp_message/__init__.py
pytcp_message/message/TcpMessage.py
pytcp_message/message/TcpRequest.py
pytcp_message/message/__init__.py
pytcp_message-0.1.9.dist-info/LICENSE
pytcp_message-0.1.9.dist-info/METADATA
pytcp_message-0.1.9.dist-info/WHEEL
pytcp_message-0.1.9.dist-info/top_level.txt
pytcp_message-0.1.9.dist-info/RECORD
