Metadata-Version: 2.1
Name: pytcp-message
Version: 0.1.9
Summary: Client and server for TCP message passing
Home-page: https://github.com/evindunn/pytcp_message
Author: Evin Dunn
Author-email: evin@scan-bugs.org
License: MIT
Platform: UNKNOWN
Requires-Python: >=3.6
